{
  "id": 1474721787,
  "question_id": 2392,
  "lang": "cpp",
  "lang_name": "C++",
  "timestamp": 1733780985,
  "status": 10,
  "status_display": "Accepted",
  "runtime": "44 ms",
  "url": "/submissions/detail/1474721787/",
  "is_pending": "Not Pending",
  "title": "Successful Pairs of Spells and Potions",
  "memory": "104.3 MB",
  "code": "class Solution {\npublic:\n\nint check(int spell, long long  sucess, vector<int> &potions)\n{\n    int lo = 0, hi = potions.size()-1, mid, ans = -1;\n\n    while (lo <= hi)\n    {\n        mid = lo + (hi - lo) / 2;\n        long long power = ( long long ) potions[mid] * spell;\n        if (power >= sucess)\n        {\n            ans = mid;\n            hi = mid - 1;\n        }\n        else\n            lo = mid + 1;\n    }\n\n    return ans;\n}\nvector<int> successfulPairs(vector<int> &spells, vector<int> &potions, long long success)\n{\n    sort(potions.begin(), potions.end());\n\n    vector<int> ans;\n    for (int i = 0; i < spells.size(); i++)\n    {\n        int k = check(spells[i], success, potions);\n\n        if (k == -1)\n            ans.push_back(0);\n        else\n            ans.push_back(potions.size() - k );\n    }\n\n    return ans;\n}\n\n};",
  "title_slug": "successful-pairs-of-spells-and-potions",
  "has_notes": false,
  "flag_type": 1
}
